pyjamaas/__init__.py
pyjamaas/cliff.py
pyjamaas/config.py
pyjamaas/log.py
pyjamaas/maas.py
pyjamaas/parse.py
pyjamaas/util.py
pyjamaas/commands/__init__.py
pyjamaas/commands/allocate.py
pyjamaas/commands/clone.py
pyjamaas/commands/config.py
pyjamaas/commands/machine.py
pyjamaas/commands/release.py
pyjamaas/commands/shell.py
pyjamaas/commands/tags.py
pyjamaas/commands/unlock.py
pyjamaas-0.6.dist-info/LICENSE
pyjamaas-0.6.dist-info/METADATA
pyjamaas-0.6.dist-info/WHEEL
pyjamaas-0.6.dist-info/entry_points.txt
pyjamaas-0.6.dist-info/top_level.txt
pyjamaas-0.6.dist-info/RECORD
