Metadata-Version: 2.1
Name: pyjamaas
Version: 0.6
Summary: Python MaaS and Juju toolkit
Home-page: https://github.com/grnet/pyjamaas.git
License: UNKNOWN
Platform: UNKNOWN
Classifier: Intended Audience :: System Administrators
Classifier: Programming Language :: Python :: 3
Classifier: Programming Language :: Python :: 3.5
Classifier: Programming Language :: Python :: 3.6
Classifier: Programming Language :: Python :: 3.7
Classifier: Programming Language :: Python :: 3.8
Classifier: License :: OSI Approved :: GNU General Public License v3 (GPLv3)
Classifier: Operating System :: OS Independent
Requires-Dist: cliff
Requires-Dist: python-libmaas
Requires-Dist: pyyaml
